{
  "availabilityDates": {
    "2021-10-05": [
      {
        "localStartTime": "09:30:00",
        "durationSeconds": 360
      },
      {
        "localStartTime": "13:42:00",
        "durationSeconds": 360
      }
    ],
    "2021-10-09": [
      {
        "localStartTime": "12:36:00",
        "durationSeconds": 360
      }
    ],
    "2021-10-30": [
      {
        "localStartTime": "09:30:00",
        "durationSeconds": 360
      }
    ]
  },
  "lastUpdatedAt": "2021-10-04T01:24:53.140Z"
}