{
  "availabilityDates": {
    "2021-09-07": [
      {
        "localStartTime": "09:54:00",
        "durationSeconds": 360
      },
      {
        "localStartTime": "10:12:00",
        "durationSeconds": 360
      },
      {
        "localStartTime": "10:18:00",
        "durationSeconds": 360
      },
      {
        "localStartTime": "10:24:00",
        "durationSeconds": 360
      },
      {
        "localStartTime": "10:30:00",
        "durationSeconds": 360
      },
      {
        "localStartTime": "10:36:00",
        "durationSeconds": 360
      },
      {
        "localStartTime": "10:42:00",
        "durationSeconds": 360
      },
      {
        "localStartTime": "10:48:00",
        "durationSeconds": 360
      },
      {
        "localStartTime": "10:54:00",
        "durationSeconds": 360
      },
      {
        "localStartTime": "11:06:00",
        "durationSeconds": 360
      },
      {
        "localStartTime": "11:12:00",
        "durationSeconds": 360
      },
      {
        "localStartTime": "11:18:00",
        "durationSeconds": 360
      },
      {
        "localStartTime": "11:36:00",
        "durationSeconds": 360
      },
      {
        "localStartTime": "13:42:00",
        "durationSeconds": 360
      },
      {
        "localStartTime": "13:48:00",
        "durationSeconds": 360
      },
      {
        "localStartTime": "13:54:00",
        "durationSeconds": 360
      },
      {
        "localStartTime": "14:12:00",
        "durationSeconds": 360
      },
      {
        "localStartTime": "14:18:00",
        "durationSeconds": 360
      },
      {
        "localStartTime": "14:24:00",
        "durationSeconds": 360
      },
      {
        "localStartTime": "14:36:00",
        "durationSeconds": 360
      },
      {
        "localStartTime": "14:42:00",
        "durationSeconds": 360
      },
      {
        "localStartTime": "14:48:00",
        "durationSeconds": 360
      },
      {
        "localStartTime": "14:54:00",
        "durationSeconds": 360
      },
      {
        "localStartTime": "15:12:00",
        "durationSeconds": 360
      }
    ],
    "2021-09-20": [
      {
        "localStartTime": "13:36:00",
        "durationSeconds": 360
      }
    ]
  },
  "lastUpdatedAt": "2021-09-07T00:36:28.345Z"
}