{
  "availabilityDates": {
    "2021-10-11": [
      {
        "localStartTime": "11:15:00",
        "durationSeconds": 900
      }
    ],
    "2021-10-21": [
      {
        "localStartTime": "15:15:00",
        "durationSeconds": 900
      }
    ],
    "2021-10-30": [
      {
        "localStartTime": "17:30:00",
        "durationSeconds": 900
      }
    ],
    "2021-11-02": [
      {
        "localStartTime": "15:00:00",
        "durationSeconds": 900
      }
    ],
    "2021-11-03": [
      {
        "localStartTime": "17:00:00",
        "durationSeconds": 900
      },
      {
        "localStartTime": "17:15:00",
        "durationSeconds": 900
      }
    ]
  },
  "lastUpdatedAt": "2021-09-06T01:52:09.488Z"
}