{
  "availabilityDates": {
    "2021-11-16": [
      {
        "localStartTime": "09:00:00",
        "durationSeconds": 600
      },
      {
        "localStartTime": "10:00:00",
        "durationSeconds": 600
      }
    ],
    "2021-11-22": [
      {
        "localStartTime": "10:30:00",
        "durationSeconds": 600
      }
    ],
    "2021-11-29": [
      {
        "localStartTime": "16:40:00",
        "durationSeconds": 600
      }
    ],
    "2021-12-03": [
      {
        "localStartTime": "09:10:00",
        "durationSeconds": 600
      }
    ]
  },
  "lastUpdatedAt": "2021-10-06T03:36:15.048Z"
}