{
  "availabilityDates": {
    "2021-09-27": [
      {
        "localStartTime": "19:40:00",
        "durationSeconds": 300
      }
    ],
    "2021-10-01": [
      {
        "localStartTime": "12:45:00",
        "durationSeconds": 300
      }
    ],
    "2021-10-13": [
      {
        "localStartTime": "14:25:00",
        "durationSeconds": 300
      }
    ],
    "2021-10-18": [
      {
        "localStartTime": "19:20:00",
        "durationSeconds": 300
      }
    ],
    "2021-10-19": [
      {
        "localStartTime": "12:35:00",
        "durationSeconds": 300
      },
      {
        "localStartTime": "12:45:00",
        "durationSeconds": 300
      }
    ],
    "2021-10-30": [
      {
        "localStartTime": "13:34:00",
        "durationSeconds": 240
      }
    ]
  },
  "lastUpdatedAt": "2021-09-09T03:54:20.176Z"
}