{
  "availabilityDates": {
    "2021-10-08": [
      {
        "localStartTime": "11:40:00",
        "durationSeconds": 300
      }
    ],
    "2021-10-19": [
      {
        "localStartTime": "10:40:00",
        "durationSeconds": 300
      }
    ],
    "2021-10-28": [
      {
        "localStartTime": "10:05:00",
        "durationSeconds": 300
      }
    ],
    "2021-10-29": [
      {
        "localStartTime": "09:55:00",
        "durationSeconds": 300
      }
    ]
  },
  "lastUpdatedAt": "2021-09-14T21:51:44.387Z"
}