{
  "availabilityDates": {
    "2021-10-04": [
      {
        "localStartTime": "09:45:00",
        "durationSeconds": 300
      },
      {
        "localStartTime": "10:45:00",
        "durationSeconds": 300
      },
      {
        "localStartTime": "11:05:00",
        "durationSeconds": 300
      },
      {
        "localStartTime": "15:40:00",
        "durationSeconds": 300
      }
    ],
    "2021-10-05": [
      {
        "localStartTime": "09:35:00",
        "durationSeconds": 300
      },
      {
        "localStartTime": "09:50:00",
        "durationSeconds": 300
      },
      {
        "localStartTime": "14:30:00",
        "durationSeconds": 300
      },
      {
        "localStartTime": "14:55:00",
        "durationSeconds": 300
      },
      {
        "localStartTime": "15:15:00",
        "durationSeconds": 300
      }
    ],
    "2021-10-06": [
      {
        "localStartTime": "11:40:00",
        "durationSeconds": 300
      }
    ]
  },
  "lastUpdatedAt": "2021-10-03T18:10:18.205Z"
}